R_plus/__init__.py
R_plus/pipeline.py
R_plus/scheme.py
R_plus/utils/log.py
R_plus/utils/tools.py
R_plus-0.1.0.dist-info/LICENSE
R_plus-0.1.0.dist-info/METADATA
R_plus-0.1.0.dist-info/WHEEL
R_plus-0.1.0.dist-info/top_level.txt
R_plus-0.1.0.dist-info/RECORD
