Metadata-Version: 2.1
Name: R_plus
Version: 0.1.0
Summary: R+ implementation
Home-page: https:/github.com/incpink-Liu/DNA-storage-R+
Author: Incpink Liu, Zhi Ping
Author-email: liuderuilin@genomics.cn, liuderuilin22@mails.ucas.ac.cn
Maintainer: BGI-research
Classifier: Intended Audience :: Science/Research
Classifier: Intended Audience :: Developers
Classifier: Intended Audience :: Education
Classifier: Programming Language :: Python :: 3
Classifier: License :: OSI Approved :: MIT License
Classifier: Operating System :: OS Independent
Classifier: Topic :: Scientific/Engineering :: Bio-Informatics
License-File: LICENSE
